AutoPy_Android/__init__.py
AutoPy_Android/xxxx.py
AutoPy_Android-1.2.0.dist-info/METADATA
AutoPy_Android-1.2.0.dist-info/WHEEL
AutoPy_Android-1.2.0.dist-info/top_level.txt
AutoPy_Android-1.2.0.dist-info/RECORD
