Metadata-Version: 2.1
Name: AutoPy-Android
Version: 1.2.0
Summary: AutoPy轻松实现python操作android,实现安卓手机自动化操作!
Home-page: UNKNOWN
Author: 1019157263@qq.com
Author-email: 1019157263@qq.com
License: MIT
Platform: UNKNOWN
Classifier: Programming Language :: Python :: 3
Classifier: License :: OSI Approved :: MIT License
Classifier: Operating System :: OS Independent
